{
  "Name": "checkboxwithtreeview",
  "Description": "Returns the information of a checkbox with treeview record in JSON object format",
  "HttpMethod": "GET",
  "IsEnabled": true,
  "OrderIndex": 62,
  "CrossDomainPolicy": "PortalAliasesOnly",
  "Input": [
    {
      "Name": "RecordId",
      "IsDeleted": false,
      "IsEnabled": true,
      "OrderIndex": 0,
      "Parameters": {},
      "InputTypeStr": "text",
      "Validations": [
        {
          "Data": "{\"Message\":\"RecordId is required.\"}",
          "Type": "default-required",
          "IsDeleted": false,
          "IsEnabled": false,
          "OrderIndex": 0,
          "Metadata": {
            "PAP_InternalIdentifier": "Api.InputField.RequiredValidator"
          }
        }
      ]
    }
  ],
  "Actions": [
    {
      "ActionType": "PlantAnApp.ReadEntity.c0e98bb5-b04c-4fb8-b68a-9a4e8ae6ffa8",
      "OrderIndex": 0,
      "Parameters": {
        "RecordId": "[RecordId]",
        "OutputToken": "Record"
      },
      "IsDisabled": false,
      "ExecutionType": "OnExecute",
      "Metadata": {
        "PAP_InternalIdentifier": "Api.ReadEntity",
        "EntityIdentifier": "c0e98bb5-b04c-4fb8-b68a-9a4e8ae6ffa8",
        "IsUidEnabled": "True"
      }
    },
    {
      "ActionType": "JsonObject",
      "OrderIndex": 1,
      "Parameters": {
        "HttpCode": "200 OK",
        "Fields": [
          {
            "name": "Id",
            "value": "[RecordId]"
          },
          {
            "name": "int",
            "value": "[Record:int]"
          },
          {
            "name": "name",
            "value": "[Record:name]"
          },
          {
            "name": "email",
            "value": "[Record:email]"
          }
        ],
        "Headers": []
      },
      "IsDisabled": false,
      "ExecutionType": "OnExecute",
      "Metadata": {
        "PAP_InternalIdentifier": "Api.Response"
      }
    }
  ],
  "OnErrorActions": []
}