{
  "Name": "ApplicationUsers",
  "Description": "Returns the information of all ApplicationUser records in JSON object format.",
  "HttpMethod": "GET",
  "IsEnabled": true,
  "OrderIndex": 83,
  "CrossDomainPolicy": "PortalAliasesOnly",
  "Input": [
    {
      "Name": "RowLimit",
      "IsDeleted": false,
      "IsEnabled": true,
      "OrderIndex": 0,
      "Parameters": {},
      "InputTypeStr": "number",
      "Validations": [
        {
          "Data": "{\"Message\":\"RowLimit is required.\"}",
          "Type": "default-required",
          "IsDeleted": false,
          "IsEnabled": false,
          "OrderIndex": 0,
          "Metadata": {
            "PAP_InternalIdentifier": "Api.InputField.RequiredValidator"
          }
        }
      ]
    }
  ],
  "Actions": [
    {
      "ActionType": "PlantAnApp.ReadAllEntity.ab411127-a835-4129-9c52-c9b1f4408b01",
      "OrderIndex": 0,
      "Parameters": {
        "OutputToken": "ApplicationUsers",
        "RowLimit": "[RowLimit]"
      },
      "IsDisabled": false,
      "ExecutionType": "OnExecute",
      "Metadata": {
        "PAP_InternalIdentifier": "Api.ReadAllEntityRecords",
        "EntityIdentifier": "ab411127-a835-4129-9c52-c9b1f4408b01",
        "IsUidEnabled": "True"
      }
    },
    {
      "ActionType": "RawResponse",
      "OrderIndex": 1,
      "Parameters": {
        "HttpCode": "200 OK",
        "Content": "{\"ApplicationUsers\" : [ApplicationUsers:json]}",
        "Headers": [
          {
            "name": "Content-Type",
            "value": "application/json"
          }
        ]
      },
      "IsDisabled": false,
      "ExecutionType": "OnExecute",
      "Metadata": {
        "PAP_InternalIdentifier": "Api.RawResponse"
      }
    }
  ],
  "OnErrorActions": []
}